alita_graphql/__init__.py
alita_graphql/graphql_view.py
alita_graphql-0.1.0.dist-info/METADATA
alita_graphql-0.1.0.dist-info/RECORD
alita_graphql-0.1.0.dist-info/WHEEL
alita_graphql-0.1.0.dist-info/top_level.txt
